------ switch_thread: currentThread at 143591356

------ dispatch special - 0 ------------------

0x88EC5C7: 
OPCODE (0xB2) getstatic

------ dispatch special - 3 ------------------

0x88EC604: 
OPCODE (0xBB) new
0x88EC607: 
OPCODE (0x59) dup
0x88EC608: 
OPCODE (0x3) iconst_0
0x88EC609: 
OPCODE (0xB7) invokespecial

------ dispatch special - 56 ------------------

0x88EC63F: 
OPCODE (0x2A) aload_0
### aload_x(thread=1, frame=2, ref=143591240): 143591210
0x88EC640: 
OPCODE (0xB7) invokespecial

------ dispatch special - 2 ------------------

0x88EC51A: 
OPCODE (0xB1) return

------ return ----- 2 ------------------

0x88EC643: 
OPCODE (0x2A) aload_0
### aload_x(thread=1, frame=2, ref=143591240): 143591210
0x88EC644: 
OPCODE (0x3) iconst_0
0x88EC645: 
OPCODE (0xB5) putfield
0x88EC648: 
OPCODE (0x2A) aload_0
### aload_x(thread=1, frame=2, ref=143591240): 143591210
0x88EC649: 
OPCODE (0x1B) iload_1
0x88EC64A: 
OPCODE (0xB5) putfield
0x88EC64D: 
OPCODE (0x2A) aload_0
### aload_x(thread=1, frame=2, ref=143591240): 143591210
0x88EC64E: 
OPCODE (0x6) iconst_3
0x88EC64F: 
OPCODE (0x11) sipush
0x88EC652: 
OPCODE (0xB6) invokevirtual

------ dispatch special - 58 ------------------

0x88EC666: 
OPCODE (0x2A) aload_0
### aload_x(thread=1, frame=3, ref=143591248): 143591210
0x88EC667: 
OPCODE (0xB4) getfield
0x88EC66A: 
OPCODE (0x1B) iload_1
0x88EC66B: 
OPCODE (0x4) iconst_1
0x88EC66C: 
OPCODE (0xB8) invokestatic

------ dispatch special - 37 ------------------

& Setting sensor 0, type LIGHT
0x88EC66F: 
OPCODE (0x2A) aload_0
### aload_x(thread=1, frame=3, ref=143591248): 143591210
0x88EC670: 
OPCODE (0xB4) getfield
0x88EC673: 
OPCODE (0x1C) iload_2
0x88EC674: 
OPCODE (0x3) iconst_0
0x88EC675: 
OPCODE (0xB8) invokestatic

------ dispatch special - 37 ------------------

& Setting sensor 0, mode = PERCENT, slope = 0
0x88EC678: 
OPCODE (0xB1) return

------ return ----- 58 ------------------

0x88EC655: 
OPCODE (0xB1) return

------ return ----- 56 ------------------

0x88EC60C: 
OPCODE (0xB3) putstatic
0x88EC60F: 
OPCODE (0xBB) new
0x88EC612: 
OPCODE (0x59) dup
0x88EC613: 
OPCODE (0x4) iconst_1
0x88EC614: 
OPCODE (0xB7) invokespecial

------ dispatch special - 56 ------------------

0x88EC63F: 
OPCODE (0x2A) aload_0
### aload_x(thread=1, frame=2, ref=143591240): 143591192
0x88EC640: 
OPCODE (0xB7) invokespecial

------ dispatch special - 2 ------------------

0x88EC51A: 
OPCODE (0xB1) return

------ return ----- 2 ------------------

0x88EC643: 
OPCODE (0x2A) aload_0
### aload_x(thread=1, frame=2, ref=143591240): 143591192
0x88EC644: 
OPCODE (0x3) iconst_0
0x88EC645: 
OPCODE (0xB5) putfield
0x88EC648: 
OPCODE (0x2A) aload_0
### aload_x(thread=1, frame=2, ref=143591240): 143591192
0x88EC649: 
OPCODE (0x1B) iload_1
0x88EC64A: 
OPCODE (0xB5) putfield
0x88EC64D: 
OPCODE (0x2A) aload_0
### aload_x(thread=1, frame=2, ref=143591240): 143591192
0x88EC64E: 
OPCODE (0x6) iconst_3
0x88EC64F: 
OPCODE (0x11) sipush
0x88EC652: 
OPCODE (0xB6) invokevirtual

------ dispatch special - 58 ------------------

0x88EC666: 
OPCODE (0x2A) aload_0
### aload_x(thread=1, frame=3, ref=143591248): 143591192
0x88EC667: 
OPCODE (0xB4) getfield
0x88EC66A: 
OPCODE (0x1B) iload_1
0x88EC66B: 
OPCODE (0x4) iconst_1
0x88EC66C: 
OPCODE (0xB8) invokestatic

------ dispatch special - 37 ------------------

& Setting sensor 1, type LIGHT
0x88EC66F: 
OPCODE (0x2A) aload_0
### aload_x(thread=1, frame=3, ref=143591248): 143591192
0x88EC670: 
OPCODE (0xB4) getfield
0x88EC673: 
OPCODE (0x1C) iload_2
0x88EC674: 
OPCODE (0x3) iconst_0
0x88EC675: 
OPCODE (0xB8) invokestatic

------ dispatch special - 37 ------------------

& Setting sensor 1, mode = PERCENT, slope = 0
0x88EC678: 
OPCODE (0xB1) return

------ return ----- 58 ------------------

0x88EC655: 
OPCODE (0xB1) return

------ return ----- 56 ------------------

0x88EC617: 
OPCODE (0xB3) putstatic
0x88EC61A: 
OPCODE (0xBB) new
0x88EC61D: 
OPCODE (0x59) dup
0x88EC61E: 
OPCODE (0x5) iconst_2
0x88EC61F: 
OPCODE (0xB7) invokespecial

------ dispatch special - 56 ------------------

0x88EC63F: 
OPCODE (0x2A) aload_0
### aload_x(thread=1, frame=2, ref=143591240): 143591174
0x88EC640: 
OPCODE (0xB7) invokespecial

------ dispatch special - 2 ------------------

0x88EC51A: 
OPCODE (0xB1) return

------ return ----- 2 ------------------

0x88EC643: 
OPCODE (0x2A) aload_0
### aload_x(thread=1, frame=2, ref=143591240): 143591174
0x88EC644: 
OPCODE (0x3) iconst_0
0x88EC645: 
OPCODE (0xB5) putfield
0x88EC648: 
OPCODE (0x2A) aload_0
### aload_x(thread=1, frame=2, ref=143591240): 143591174
0x88EC649: 
OPCODE (0x1B) iload_1
0x88EC64A: 
OPCODE (0xB5) putfield
0x88EC64D: 
OPCODE (0x2A) aload_0
### aload_x(thread=1, frame=2, ref=143591240): 143591174
0x88EC64E: 
OPCODE (0x6) iconst_3
0x88EC64F: 
OPCODE (0x11) sipush
0x88EC652: 
OPCODE (0xB6) invokevirtual

------ dispatch special - 58 ------------------

0x88EC666: 
OPCODE (0x2A) aload_0
### aload_x(thread=1, frame=3, ref=143591248): 143591174
0x88EC667: 
OPCODE (0xB4) getfield
0x88EC66A: 
OPCODE (0x1B) iload_1
0x88EC66B: 
OPCODE (0x4) iconst_1
0x88EC66C: 
OPCODE (0xB8) invokestatic

------ dispatch special - 37 ------------------

& Setting sensor 2, type LIGHT
0x88EC66F: 
OPCODE (0x2A) aload_0
### aload_x(thread=1, frame=3, ref=143591248): 143591174
0x88EC670: 
OPCODE (0xB4) getfield
0x88EC673: 
OPCODE (0x1C) iload_2
0x88EC674: 
OPCODE (0x3) iconst_0
0x88EC675: 
OPCODE (0xB8) invokestatic

------ dispatch special - 37 ------------------

& Setting sensor 2, mode = PERCENT, slope = 0
0x88EC678: 
OPCODE (0xB1) return

------ return ----- 58 ------------------

0x88EC655: 
OPCODE (0xB1) return

------ return ----- 56 ------------------

0x88EC622: 
OPCODE (0xB3) putstatic
0x88EC625: 
OPCODE (0x6) iconst_3
0x88EC626: 
OPCODE (0xBC) newarray
0x88EC628: 
OPCODE (0x0) nop
0x88EC629: 
OPCODE (0x59) dup
0x88EC62A: 
OPCODE (0x3) iconst_0
0x88EC62B: 
OPCODE (0xB2) getstatic
0x88EC62E: 
OPCODE (0x53) aastore
0x88EC62F: 
OPCODE (0x59) dup
0x88EC630: 
OPCODE (0x4) iconst_1
0x88EC631: 
OPCODE (0xB2) getstatic
0x88EC634: 
OPCODE (0x53) aastore
0x88EC635: 
OPCODE (0x59) dup
0x88EC636: 
OPCODE (0x5) iconst_2
0x88EC637: 
OPCODE (0xB2) getstatic
0x88EC63A: 
OPCODE (0x53) aastore
0x88EC63B: 
OPCODE (0xB3) putstatic
0x88EC63E: 
OPCODE (0xB1) return

------ return ----- 3 ------------------

0x88EC5C7: 
OPCODE (0xB2) getstatic
0x88EC5CA: 
OPCODE (0xB6) invokevirtual

------ dispatch special - 57 ------------------

0x88EC656: 
OPCODE (0x11) sipush
0x88EC659: 
OPCODE (0x11) sipush
0x88EC65C: 
OPCODE (0x2A) aload_0
### aload_x(thread=1, frame=1, ref=143591236): 143591174
0x88EC65D: 
OPCODE (0xB4) getfield
0x88EC660: 
OPCODE (0x60) iadd
0x88EC661: 
OPCODE (0x93) i2s
0x88EC662: 
OPCODE (0xB8) invokestatic

------ dispatch special - 27 ------------------

& ROM call 1: 0x19C4 (4098)
0x88EC665: 
OPCODE (0xB1) return

------ return ----- 57 ------------------

0x88EC5CD: 
OPCODE (0xB1) return

------ return ----- 0 ------------------

------ switch_thread: currentThread at 143591356
